Metadata-Version: 1.0
Name: toggl-jira-sync
Version: 0.0.5
Summary: Sync Toggl with JIRA
Home-page: https://github.com/qsweber/toggl-jira-sync
Author: Quinn Weber
Author-email: quinn@quinnweber.com
License: UNKNOWN
Platform: UNKNOWN
